odoo_lve/__init__.py
odoo_lve/__manifest__.py
odoo_lve/data/lve_tributary_units.xml
odoo_lve/data/lve_withholding_concepts.xml
odoo_lve/data/lve_withholding_types.xml
odoo_lve/data/template/account.account-generic_coa.csv
odoo_lve/data/template/account.tax-generic_coa.csv
odoo_lve/data/template/account.tax.group.csv
odoo_lve/data/template/res.country.state.csv
odoo_lve/models/__init__.py
odoo_lve/models/lve_tributary_unit.py
odoo_lve/models/lve_utils.py
odoo_lve/models/lve_withholding_concept.py
odoo_lve/models/lve_withholding_rate.py
odoo_lve/models/lve_withholding_type.py
odoo_lve/security/ir.model.access.csv
odoo_lve/views/lve_menus.xml
odoo_lve/views/lve_tributary_unit_views.xml
odoo_lve/views/lve_withholding_concept_views.xml
odoo_lve/views/lve_withholding_type_views.xml
odoo_lve-1.0.0.dist-info/licenses/LICENSE
tests/__init__.py
tests/test_basic.py
odoo_lve-1.0.0.dist-info/METADATA
odoo_lve-1.0.0.dist-info/WHEEL
odoo_lve-1.0.0.dist-info/top_level.txt
odoo_lve-1.0.0.dist-info/RECORD
