Metadata-Version: 2.4
Name: odoo_lve
Version: 1.0.0
Summary: Venezuela Location module for Odoo
Home-page: https://github.com/erpcya/odoo_lve
Author: Carlos Parada
Author-email: Carlos Parada <cparada@erpya.com>
Maintainer-email: ERP Consultores y Asociados <cparada@erpya.com>
License: LGPL-3
Project-URL: Homepage, https://github.com/erpcya/odoo_lve
Project-URL: Documentation, https://github.com/erpcya/odoo_lve#readme
Project-URL: Repository, https://github.com/erpcya/odoo_lve
Project-URL: Bug Tracker, https://github.com/erpcya/odoo_lve/issues
Keywords: odoo,venezuela,location,tributary,withholding
Classifier: Development Status :: 4 - Beta
Classifier: Intended Audience :: Developers
Classifier: License :: OSI Approved :: GNU Lesser General Public License v3 (LGPLv3)
Classifier: Operating System :: OS Independent
Classifier: Programming Language :: Python :: 3
Classifier: Programming Language :: Python :: 3.8
Classifier: Programming Language :: Python :: 3.9
Classifier: Programming Language :: Python :: 3.10
Classifier: Programming Language :: Python :: 3.11
Classifier: Topic :: Office/Business :: Financial :: Accounting
Requires-Python: >=3.8
License-File: LICENSE
Provides-Extra: dev
Requires-Dist: pytest>=7.0; extra == "dev"
Requires-Dist: pytest-cov>=4.0; extra == "dev"
Requires-Dist: black>=22.0; extra == "dev"
Requires-Dist: flake8>=5.0; extra == "dev"
Requires-Dist: mypy>=1.0; extra == "dev"
Requires-Dist: pre-commit>=2.0; extra == "dev"
Dynamic: author
Dynamic: home-page
Dynamic: license-file
Dynamic: requires-python
